pysgpp/pysgpp_swig.py
pysgpp/_pysgpp_swig.so
pysgpp/__init__.py
pysgpp/extensions/__init__.py
pysgpp/extensions/datadriven/__init__.py
pysgpp/extensions/datadriven/tools.py
pysgpp/extensions/datadriven/learner/LearnedKnowledge.py
pysgpp/extensions/datadriven/learner/Learner.py
pysgpp/extensions/datadriven/learner/Types.py
pysgpp/extensions/datadriven/learner/Classifier.py
pysgpp/extensions/datadriven/learner/__init__.py
pysgpp/extensions/datadriven/learner/TrainingSpecification.py
pysgpp/extensions/datadriven/learner/Regressor.py
pysgpp/extensions/datadriven/learner/TrainingStopPolicy.py
pysgpp/extensions/datadriven/learner/LearnerBuilder.py
pysgpp/extensions/datadriven/learner/folding/StratifiedFoldingPolicy.py
pysgpp/extensions/datadriven/learner/folding/FilesFoldingPolicy.py
pysgpp/extensions/datadriven/learner/folding/RandomFoldingPolicy.py
pysgpp/extensions/datadriven/learner/folding/__init__.py
pysgpp/extensions/datadriven/learner/folding/FoldingPolicy.py
pysgpp/extensions/datadriven/learner/folding/SequentialFoldingPolicy.py
pysgpp/extensions/datadriven/learner/formatter/LearnedKnowledgeFormatter.py
pysgpp/extensions/datadriven/learner/formatter/LearnerFormatter.py
pysgpp/extensions/datadriven/learner/formatter/__init__.py
pysgpp/extensions/datadriven/learner/formatter/GridImageFormatter.py
pysgpp/extensions/datadriven/learner/formatter/GridFormatter.py
pysgpp/extensions/datadriven/learner/solver/CGSolver.py
pysgpp/extensions/datadriven/learner/solver/__init__.py
pysgpp/extensions/datadriven/learner/solver/LinearSolver.py
pysgpp/extensions/datadriven/controller/LearnerEventController.py
pysgpp/extensions/datadriven/controller/InfoToScreen.py
pysgpp/extensions/datadriven/controller/SolverEventController.py
pysgpp/extensions/datadriven/controller/InfoToScreenRegressor.py
pysgpp/extensions/datadriven/controller/__init__.py
pysgpp/extensions/datadriven/controller/CheckpointController.py
pysgpp-3.3.0.dist-info/RECORD
pysgpp-3.3.0.dist-info/LICENSE.md
pysgpp-3.3.0.dist-info/WHEEL
pysgpp-3.3.0.dist-info/top_level.txt
pysgpp-3.3.0.dist-info/METADATA
