Metadata-Version: 2.1
Name: pysgpp
Version: 3.3.0
Summary: The sparse grids toolkit SG++
Home-page: https://github.com/SGpp/SGpp
Author: Dirk.Pflueger@ipvs.uni-stuttgart.de
License: BSD-style license
Platform: UNKNOWN
